[
			{
				"name":"农庄体验家庭日",
				"text1":"产地直供",
				"text2":"促销",
				"produceArea":"产地：崇明",
				"price":"￥150.00",
				"src":"img/g5.jpg",
				"introduce":"陪伴一整个冬天的草莓就要下市啦，来农庄种菜，抓住草莓的尾巴",
				"productData":"5"
			},
			{
				"name":"恒馨绿色香米 大米-5kg",
				"text1":"原生态",
				"text2":"促销",
				"produceArea":"产地：中国江苏",
				"price":"￥138.00",
				"src":"img/g6.jpg",
				"introduce":"产自鱼米之乡江苏句容，选用优质香米品种，采用有机种植方式种植，采用全自动分选包装工艺，确保大米质量",
				"productData":"6"
			},
			{
				"name":"陕西高原红富士4个装",
				"text1":"原生态",
				"text2":"促销",
				"produceArea":"产地：陕西",
				"price":"￥29.80",
				"src":"img/g7.jpg",
				"introduce":"精选陕西红富士，其果形扁圆， 果肉黄白色，肉质致密，细脆、果汁多。酸甜适口，芳香味浓，品质极上",
				"productData":"7"
			},
			{
				"name":"有机林地散养土鸡蛋-10枚",
				"text1":"有机",
				"text2":"促销",
				"produceArea":"产地：安徽",
				"price":"￥36.00",
				"src":"img/g8.jpg",
				"introduce":"无抗生素、无生长激素添加的有机散养土鸡蛋蛋清稠密、蛋黄大且浓厚香醇，吃起来有黏牙的感觉，营养价值极高。",
				"productData":"8"
			}



		]






